{
  "contributors": [
    {
      "attempt_yield": 0.3179,
      "attempts": 173,
      "difficulty_points": 110,
      "failed_attempts": 118,
      "failures": 99,
      "median_solve_s": 293,
      "p90_solve_s": 1914,
      "run_success_rate": 0.3571,
      "runs": 154,
      "solver": "cgbarlow",
      "successes": 55,
      "successes_per_recorded_hour": 1.846,
      "total_solve_s": 107269,
      "verified_proofs": 52
    },
    {
      "attempt_yield": 0.4091,
      "attempts": 44,
      "difficulty_points": 29,
      "failed_attempts": 26,
      "failures": 8,
      "median_solve_s": 392,
      "p90_solve_s": 926,
      "run_success_rate": 0.6923,
      "runs": 26,
      "solver": "perttu",
      "successes": 18,
      "successes_per_recorded_hour": 3.954,
      "total_solve_s": 16388,
      "verified_proofs": 15
    },
    {
      "attempt_yield": 0.0606,
      "attempts": 33,
      "difficulty_points": 10,
      "failed_attempts": 31,
      "failures": 20,
      "median_solve_s": 283,
      "p90_solve_s": 530,
      "run_success_rate": 0.0909,
      "runs": 22,
      "solver": "adam91holt",
      "successes": 2,
      "successes_per_recorded_hour": 1.013,
      "total_solve_s": 7107,
      "verified_proofs": 6
    },
    {
      "attempt_yield": 1.0,
      "attempts": 1,
      "difficulty_points": 1,
      "failed_attempts": 0,
      "failures": 0,
      "median_solve_s": 463,
      "p90_solve_s": 463,
      "run_success_rate": 1.0,
      "runs": 1,
      "solver": "yarcles",
      "successes": 1,
      "successes_per_recorded_hour": 7.775,
      "total_solve_s": 463,
      "verified_proofs": 1
    }
  ],
  "coverage": {
    "attributed_proofs": 74,
    "historical_unknown_proofs": 102,
    "proof_run_coverage": 0.4318,
    "successful_proofs_with_run_telemetry": 76,
    "terminal_runs": 203,
    "verified_proofs": 176
  },
  "credit": {
    "credited_contributors": 8,
    "credited_proofs": 176,
    "explicit_solver_proofs": 74,
    "inferred_git_proofs": 102,
    "uncredited_proofs": 0
  },
  "credited_contributors": [
    {
      "attempt_yield": 0.3179,
      "attempts": 173,
      "avatar_url": "https://github.com/cgbarlow.png?size=96",
      "credit_source_summary": "explicit + inferred",
      "credit_sources": [
        "explicit-solver",
        "inferred-git-add-author"
      ],
      "credited_proofs": 98,
      "difficulty_points": 168,
      "display_name": "@cgbarlow",
      "explicit_solver_proofs": 52,
      "failed_attempts": 118,
      "failures": 99,
      "git_author": "Chris Barlow <cgbarlow@gmail.com>",
      "github": "cgbarlow",
      "inferred_git_proofs": 46,
      "median_solve_s": 293,
      "p90_solve_s": 1914,
      "profile_url": "https://github.com/cgbarlow",
      "run_success_rate": 0.3571,
      "runs": 154,
      "solver": "cgbarlow",
      "successes": 55,
      "successes_per_recorded_hour": 1.846,
      "total_solve_s": 107269,
      "verified_proofs": 98
    },
    {
      "attempt_yield": null,
      "attempts": 0,
      "avatar_url": "https://github.com/chat-bit-01.png?size=96",
      "credit_source_summary": "inferred",
      "credit_sources": [
        "inferred-git-add-author"
      ],
      "credited_proofs": 43,
      "difficulty_points": 87,
      "display_name": "@chat-bit-01",
      "explicit_solver_proofs": 0,
      "failed_attempts": 0,
      "failures": 0,
      "git_author": "chat-bit-01 <chatuser55@gmail.com>",
      "github": "chat-bit-01",
      "inferred_git_proofs": 43,
      "median_solve_s": null,
      "p90_solve_s": null,
      "profile_url": "https://github.com/chat-bit-01",
      "run_success_rate": null,
      "runs": 0,
      "solver": "chat-bit-01",
      "successes": 0,
      "successes_per_recorded_hour": null,
      "total_solve_s": 0,
      "verified_proofs": 43
    },
    {
      "attempt_yield": 0.4091,
      "attempts": 44,
      "avatar_url": "https://github.com/perttu.png?size=96",
      "credit_source_summary": "explicit",
      "credit_sources": [
        "explicit-solver"
      ],
      "credited_proofs": 15,
      "difficulty_points": 29,
      "display_name": "@perttu",
      "explicit_solver_proofs": 15,
      "failed_attempts": 26,
      "failures": 8,
      "git_author": null,
      "github": "perttu",
      "inferred_git_proofs": 0,
      "median_solve_s": 392,
      "p90_solve_s": 926,
      "profile_url": "https://github.com/perttu",
      "run_success_rate": 0.6923,
      "runs": 26,
      "solver": "perttu",
      "successes": 18,
      "successes_per_recorded_hour": 3.954,
      "total_solve_s": 16388,
      "verified_proofs": 15
    },
    {
      "attempt_yield": null,
      "attempts": 0,
      "avatar_url": "https://github.com/binto.png?size=96",
      "credit_source_summary": "inferred",
      "credit_sources": [
        "inferred-git-add-author"
      ],
      "credited_proofs": 9,
      "difficulty_points": 19,
      "display_name": "@binto",
      "explicit_solver_proofs": 0,
      "failed_attempts": 0,
      "failures": 0,
      "git_author": "binto <marcjvincent@gmail.com>",
      "github": "binto",
      "inferred_git_proofs": 9,
      "median_solve_s": null,
      "p90_solve_s": null,
      "profile_url": "https://github.com/binto",
      "run_success_rate": null,
      "runs": 0,
      "solver": "binto",
      "successes": 0,
      "successes_per_recorded_hour": null,
      "total_solve_s": 0,
      "verified_proofs": 9
    },
    {
      "attempt_yield": 0.0606,
      "attempts": 33,
      "avatar_url": "https://github.com/adam91holt.png?size=96",
      "credit_source_summary": "explicit",
      "credit_sources": [
        "explicit-solver"
      ],
      "credited_proofs": 6,
      "difficulty_points": 10,
      "display_name": "@adam91holt",
      "explicit_solver_proofs": 6,
      "failed_attempts": 31,
      "failures": 20,
      "git_author": null,
      "github": "adam91holt",
      "inferred_git_proofs": 0,
      "median_solve_s": 283,
      "p90_solve_s": 530,
      "profile_url": "https://github.com/adam91holt",
      "run_success_rate": 0.0909,
      "runs": 22,
      "solver": "adam91holt",
      "successes": 2,
      "successes_per_recorded_hour": 1.013,
      "total_solve_s": 7107,
      "verified_proofs": 6
    },
    {
      "attempt_yield": null,
      "attempts": 0,
      "avatar_url": null,
      "credit_source_summary": "inferred",
      "credit_sources": [
        "inferred-git-add-author"
      ],
      "credited_proofs": 3,
      "difficulty_points": 6,
      "display_name": "Perttu Isotalo",
      "explicit_solver_proofs": 0,
      "failed_attempts": 0,
      "failures": 0,
      "git_author": "Perttu Isotalo <pisotalo@isotalo.org>",
      "github": null,
      "inferred_git_proofs": 3,
      "median_solve_s": null,
      "p90_solve_s": null,
      "profile_url": null,
      "run_success_rate": null,
      "runs": 0,
      "solver": null,
      "successes": 0,
      "successes_per_recorded_hour": null,
      "total_solve_s": 0,
      "verified_proofs": 3
    },
    {
      "attempt_yield": null,
      "attempts": 0,
      "avatar_url": "https://github.com/OceanLi.png?size=96",
      "credit_source_summary": "inferred",
      "credit_sources": [
        "inferred-git-add-author"
      ],
      "credited_proofs": 1,
      "difficulty_points": 3,
      "display_name": "@OceanLi",
      "explicit_solver_proofs": 0,
      "failed_attempts": 0,
      "failures": 0,
      "git_author": "OceanLi <quantocean.li@gmail.com>",
      "github": "OceanLi",
      "inferred_git_proofs": 1,
      "median_solve_s": null,
      "p90_solve_s": null,
      "profile_url": "https://github.com/OceanLi",
      "run_success_rate": null,
      "runs": 0,
      "solver": "OceanLi",
      "successes": 0,
      "successes_per_recorded_hour": null,
      "total_solve_s": 0,
      "verified_proofs": 1
    },
    {
      "attempt_yield": 1.0,
      "attempts": 1,
      "avatar_url": "https://github.com/yarcles.png?size=96",
      "credit_source_summary": "explicit",
      "credit_sources": [
        "explicit-solver"
      ],
      "credited_proofs": 1,
      "difficulty_points": 1,
      "display_name": "@yarcles",
      "explicit_solver_proofs": 1,
      "failed_attempts": 0,
      "failures": 0,
      "git_author": null,
      "github": "yarcles",
      "inferred_git_proofs": 0,
      "median_solve_s": 463,
      "p90_solve_s": 463,
      "profile_url": "https://github.com/yarcles",
      "run_success_rate": 1.0,
      "runs": 1,
      "solver": "yarcles",
      "successes": 1,
      "successes_per_recorded_hour": 7.775,
      "total_solve_s": 463,
      "verified_proofs": 1
    }
  ],
  "daily": [
    {
      "attempt_yield": 0.5278,
      "attempts": 36,
      "date": "2026-06-13",
      "failed_attempts": 17,
      "failures": 3,
      "median_solve_s": 483,
      "p90_solve_s": 1227,
      "run_success_rate": 0.8636,
      "runs": 22,
      "successes": 19,
      "successes_per_recorded_hour": 4.812,
      "total_solve_s": 14214
    },
    {
      "attempt_yield": 0.1855,
      "attempts": 124,
      "date": "2026-06-14",
      "failed_attempts": 101,
      "failures": 81,
      "median_solve_s": 289,
      "p90_solve_s": 1903,
      "run_success_rate": 0.2212,
      "runs": 104,
      "successes": 23,
      "successes_per_recorded_hour": 1.329,
      "total_solve_s": 62299
    },
    {
      "attempt_yield": 0.3736,
      "attempts": 91,
      "date": "2026-06-15",
      "failed_attempts": 57,
      "failures": 43,
      "median_solve_s": 326,
      "p90_solve_s": 1914,
      "run_success_rate": 0.4416,
      "runs": 77,
      "successes": 34,
      "successes_per_recorded_hour": 2.237,
      "total_solve_s": 54714
    }
  ],
  "difficulty": [
    {
      "attempt_yield": 0.3333,
      "attempts": 81,
      "difficulty": 1,
      "failed_attempts": 54,
      "failures": 37,
      "median_solve_s": 285,
      "p90_solve_s": 1916,
      "run_success_rate": 0.4219,
      "runs": 64,
      "successes": 27,
      "successes_per_recorded_hour": 2.53,
      "total_solve_s": 38421
    },
    {
      "attempt_yield": 0.23,
      "attempts": 100,
      "difficulty": 2,
      "failed_attempts": 77,
      "failures": 60,
      "median_solve_s": 299,
      "p90_solve_s": 1897,
      "run_success_rate": 0.2771,
      "runs": 83,
      "successes": 23,
      "successes_per_recorded_hour": 1.548,
      "total_solve_s": 53505
    },
    {
      "attempt_yield": 0.44,
      "attempts": 50,
      "difficulty": 3,
      "failed_attempts": 28,
      "failures": 16,
      "median_solve_s": 348,
      "p90_solve_s": 1493,
      "run_success_rate": 0.5789,
      "runs": 38,
      "successes": 22,
      "successes_per_recorded_hour": 3.696,
      "total_solve_s": 21426
    },
    {
      "attempt_yield": 0.2105,
      "attempts": 19,
      "difficulty": 4,
      "failed_attempts": 15,
      "failures": 13,
      "median_solve_s": 569,
      "p90_solve_s": 1925,
      "run_success_rate": 0.2353,
      "runs": 17,
      "successes": 4,
      "successes_per_recorded_hour": 0.901,
      "total_solve_s": 15987
    },
    {
      "attempt_yield": 0.0,
      "attempts": 1,
      "difficulty": 5,
      "failed_attempts": 1,
      "failures": 1,
      "median_solve_s": 1888,
      "p90_solve_s": 1888,
      "run_success_rate": 0.0,
      "runs": 1,
      "successes": 0,
      "successes_per_recorded_hour": 0.0,
      "total_solve_s": 1888
    }
  ],
  "effort": [
    {
      "attempt_yield": 0.3871,
      "attempts": 155,
      "effort": "high",
      "failed_attempts": 95,
      "failures": 94,
      "median_solve_s": 291,
      "p90_solve_s": 1912,
      "run_success_rate": 0.3896,
      "runs": 154,
      "successes": 60,
      "successes_per_recorded_hour": 2.201,
      "total_solve_s": 98138
    },
    {
      "attempt_yield": 0.0741,
      "attempts": 27,
      "effort": "max",
      "failed_attempts": 25,
      "failures": 7,
      "median_solve_s": 1227,
      "p90_solve_s": 2390,
      "run_success_rate": 0.2222,
      "runs": 9,
      "successes": 2,
      "successes_per_recorded_hour": 0.613,
      "total_solve_s": 11753
    },
    {
      "attempt_yield": 0.4615,
      "attempts": 13,
      "effort": "medium",
      "failed_attempts": 7,
      "failures": 7,
      "median_solve_s": 203,
      "p90_solve_s": 297,
      "run_success_rate": 0.4615,
      "runs": 13,
      "successes": 6,
      "successes_per_recorded_hour": 8.081,
      "total_solve_s": 2673
    },
    {
      "attempt_yield": 1.0,
      "attempts": 1,
      "effort": "unknown",
      "failed_attempts": 0,
      "failures": 0,
      "median_solve_s": 463,
      "p90_solve_s": 463,
      "run_success_rate": 1.0,
      "runs": 1,
      "successes": 1,
      "successes_per_recorded_hour": 7.775,
      "total_solve_s": 463
    },
    {
      "attempt_yield": 0.1273,
      "attempts": 55,
      "effort": "xhigh",
      "failed_attempts": 48,
      "failures": 19,
      "median_solve_s": 489,
      "p90_solve_s": 1103,
      "run_success_rate": 0.2692,
      "runs": 26,
      "successes": 7,
      "successes_per_recorded_hour": 1.385,
      "total_solve_s": 18200
    }
  ],
  "goal_effort": [
    {
      "attempt_yield": 0.0,
      "attempts": 8,
      "difficulty": 2,
      "failed_attempts": 8,
      "failures": 4,
      "goal": "am-hm-two-var",
      "median_solve_s": 545,
      "p90_solve_s": 1914,
      "run_success_rate": 0.0,
      "runs": 4,
      "status": "open",
      "successes": 0,
      "successes_per_recorded_hour": 0.0,
      "total_solve_s": 3237
    },
    {
      "attempt_yield": 0.0,
      "attempts": 6,
      "difficulty": 1,
      "failed_attempts": 6,
      "failures": 2,
      "goal": "sq-add-sq-eq-three-mul-sq-s4",
      "median_solve_s": 1643,
      "p90_solve_s": 2390,
      "run_success_rate": 0.0,
      "runs": 2,
      "status": "open",
      "successes": 0,
      "successes_per_recorded_hour": 0.0,
      "total_solve_s": 3287
    },
    {
      "attempt_yield": 0.0,
      "attempts": 5,
      "difficulty": 1,
      "failed_attempts": 5,
      "failures": 3,
      "goal": "am-gm-three-cube-s2-s2",
      "median_solve_s": 392,
      "p90_solve_s": 2083,
      "run_success_rate": 0.0,
      "runs": 3,
      "status": "open",
      "successes": 0,
      "successes_per_recorded_hour": 0.0,
      "total_solve_s": 2693
    },
    {
      "attempt_yield": 0.1667,
      "attempts": 6,
      "difficulty": 2,
      "failed_attempts": 5,
      "failures": 3,
      "goal": "consecutive-cubes-diff-odd",
      "median_solve_s": 326,
      "p90_solve_s": 926,
      "run_success_rate": 0.25,
      "runs": 4,
      "status": "proved",
      "successes": 1,
      "successes_per_recorded_hour": 2.071,
      "total_solve_s": 1738
    },
    {
      "attempt_yield": 0.0,
      "attempts": 4,
      "difficulty": 2,
      "failed_attempts": 4,
      "failures": 2,
      "goal": "four-var-qm-am",
      "median_solve_s": 3187,
      "p90_solve_s": 4497,
      "run_success_rate": 0.0,
      "runs": 2,
      "status": "blocked",
      "successes": 0,
      "successes_per_recorded_hour": 0.0,
      "total_solve_s": 6375
    },
    {
      "attempt_yield": 0.0,
      "attempts": 4,
      "difficulty": 1,
      "failed_attempts": 4,
      "failures": 2,
      "goal": "nesbitt-inequality-s1",
      "median_solve_s": 1410,
      "p90_solve_s": 1959,
      "run_success_rate": 0.0,
      "runs": 2,
      "status": "open",
      "successes": 0,
      "successes_per_recorded_hour": 0.0,
      "total_solve_s": 2820
    },
    {
      "attempt_yield": 0.0,
      "attempts": 4,
      "difficulty": 1,
      "failed_attempts": 4,
      "failures": 2,
      "goal": "am-gm-three-cube-s2",
      "median_solve_s": 1318,
      "p90_solve_s": 1964,
      "run_success_rate": 0.0,
      "runs": 2,
      "status": "blocked",
      "successes": 0,
      "successes_per_recorded_hour": 0.0,
      "total_solve_s": 2637
    },
    {
      "attempt_yield": 0.0,
      "attempts": 4,
      "difficulty": 2,
      "failed_attempts": 4,
      "failures": 2,
      "goal": "coprime-2n1-2n3",
      "median_solve_s": 1312,
      "p90_solve_s": 1914,
      "run_success_rate": 0.0,
      "runs": 2,
      "status": "open",
      "successes": 0,
      "successes_per_recorded_hour": 0.0,
      "total_solve_s": 2624
    },
    {
      "attempt_yield": 0.2,
      "attempts": 5,
      "difficulty": 3,
      "failed_attempts": 4,
      "failures": 2,
      "goal": "discriminant-nonneg",
      "median_solve_s": 575,
      "p90_solve_s": 1493,
      "run_success_rate": 0.3333,
      "runs": 3,
      "status": "proved",
      "successes": 1,
      "successes_per_recorded_hour": 1.538,
      "total_solve_s": 2341
    },
    {
      "attempt_yield": 0.0,
      "attempts": 4,
      "difficulty": 2,
      "failed_attempts": 4,
      "failures": 2,
      "goal": "cube-sum-ge-three-prod",
      "median_solve_s": 510,
      "p90_solve_s": 736,
      "run_success_rate": 0.0,
      "runs": 2,
      "status": "blocked",
      "successes": 0,
      "successes_per_recorded_hour": 0.0,
      "total_solve_s": 1020
    },
    {
      "attempt_yield": 0.0,
      "attempts": 4,
      "difficulty": 3,
      "failed_attempts": 4,
      "failures": 2,
      "goal": "am-gm-three-cube",
      "median_solve_s": 496,
      "p90_solve_s": 736,
      "run_success_rate": 0.0,
      "runs": 2,
      "status": "blocked",
      "successes": 0,
      "successes_per_recorded_hour": 0.0,
      "total_solve_s": 992
    },
    {
      "attempt_yield": 0.0,
      "attempts": 4,
      "difficulty": 2,
      "failed_attempts": 4,
      "failures": 2,
      "goal": "cube-sum-ge-mul-sq",
      "median_solve_s": 173,
      "p90_solve_s": 253,
      "run_success_rate": 0.0,
      "runs": 2,
      "status": "proved",
      "successes": 0,
      "successes_per_recorded_hour": 0.0,
      "total_solve_s": 347
    },
    {
      "attempt_yield": 0.0,
      "attempts": 3,
      "difficulty": 1,
      "failed_attempts": 3,
      "failures": 3,
      "goal": "cube-sum-ge-three-prod-s1",
      "median_solve_s": 1916,
      "p90_solve_s": 1924,
      "run_success_rate": 0.0,
      "runs": 3,
      "status": "proved",
      "successes": 0,
      "successes_per_recorded_hour": 0.0,
      "total_solve_s": 4015
    },
    {
      "attempt_yield": 0.25,
      "attempts": 4,
      "difficulty": 4,
      "failed_attempts": 3,
      "failures": 1,
      "goal": "descartes-total-angular-defect",
      "median_solve_s": 742,
      "p90_solve_s": 1190,
      "run_success_rate": 0.5,
      "runs": 2,
      "status": "proved",
      "successes": 1,
      "successes_per_recorded_hour": 2.426,
      "total_solve_s": 1484
    },
    {
      "attempt_yield": 0.0,
      "attempts": 3,
      "difficulty": 3,
      "failed_attempts": 3,
      "failures": 1,
      "goal": "fourth-power-mod-five",
      "median_solve_s": 1227,
      "p90_solve_s": 1227,
      "run_success_rate": 0.0,
      "runs": 1,
      "status": "archived",
      "successes": 0,
      "successes_per_recorded_hour": 0.0,
      "total_solve_s": 1227
    },
    {
      "attempt_yield": 0.0,
      "attempts": 3,
      "difficulty": 2,
      "failed_attempts": 3,
      "failures": 1,
      "goal": "cube-eq-triangular-sq-diff",
      "median_solve_s": 889,
      "p90_solve_s": 889,
      "run_success_rate": 0.0,
      "runs": 1,
      "status": "archived",
      "successes": 0,
      "successes_per_recorded_hour": 0.0,
      "total_solve_s": 889
    },
    {
      "attempt_yield": 0.0,
      "attempts": 3,
      "difficulty": 1,
      "failed_attempts": 3,
      "failures": 1,
      "goal": "nat-sq-lt-two-pow-s2",
      "median_solve_s": 555,
      "p90_solve_s": 555,
      "run_success_rate": 0.0,
      "runs": 1,
      "status": "open",
      "successes": 0,
      "successes_per_recorded_hour": 0.0,
      "total_solve_s": 555
    },
    {
      "attempt_yield": 0.0,
      "attempts": 2,
      "difficulty": 4,
      "failed_attempts": 2,
      "failures": 2,
      "goal": "prod-one-sub-inv-sq-telescope",
      "median_solve_s": 1939,
      "p90_solve_s": 1953,
      "run_success_rate": 0.0,
      "runs": 2,
      "status": "open",
      "successes": 0,
      "successes_per_recorded_hour": 0.0,
      "total_solve_s": 3878
    },
    {
      "attempt_yield": 0.0,
      "attempts": 2,
      "difficulty": 1,
      "failed_attempts": 2,
      "failures": 2,
      "goal": "sum-icc-choose-hockey-stick-s1",
      "median_solve_s": 1907,
      "p90_solve_s": 1912,
      "run_success_rate": 0.0,
      "runs": 2,
      "status": "open",
      "successes": 0,
      "successes_per_recorded_hour": 0.0,
      "total_solve_s": 3815
    },
    {
      "attempt_yield": 0.0,
      "attempts": 2,
      "difficulty": 4,
      "failed_attempts": 2,
      "failures": 2,
      "goal": "dvd-2730-pow-thirteen-sub-self",
      "median_solve_s": 1897,
      "p90_solve_s": 1904,
      "run_success_rate": 0.0,
      "runs": 2,
      "status": "open",
      "successes": 0,
      "successes_per_recorded_hour": 0.0,
      "total_solve_s": 3794
    },
    {
      "attempt_yield": 0.0,
      "attempts": 2,
      "difficulty": 4,
      "failed_attempts": 2,
      "failures": 2,
      "goal": "abstract-regular-polyhedron-realizable-iff",
      "median_solve_s": 1371,
      "p90_solve_s": 1902,
      "run_success_rate": 0.0,
      "runs": 2,
      "status": "open",
      "successes": 0,
      "successes_per_recorded_hour": 0.0,
      "total_solve_s": 2743
    },
    {
      "attempt_yield": 0.0,
      "attempts": 2,
      "difficulty": 2,
      "failed_attempts": 2,
      "failures": 2,
      "goal": "dvd-sixty-pow-ten-sub-sq",
      "median_solve_s": 1169,
      "p90_solve_s": 1935,
      "run_success_rate": 0.0,
      "runs": 2,
      "status": "open",
      "successes": 0,
      "successes_per_recorded_hour": 0.0,
      "total_solve_s": 2338
    },
    {
      "attempt_yield": 0.3333,
      "attempts": 3,
      "difficulty": 1,
      "failed_attempts": 2,
      "failures": 2,
      "goal": "discriminant-nonneg-s2",
      "median_solve_s": 213,
      "p90_solve_s": 1902,
      "run_success_rate": 0.3333,
      "runs": 3,
      "status": "proved",
      "successes": 1,
      "successes_per_recorded_hour": 1.579,
      "total_solve_s": 2280
    },
    {
      "attempt_yield": 0.3333,
      "attempts": 3,
      "difficulty": 2,
      "failed_attempts": 2,
      "failures": 2,
      "goal": "four-consecutive-product-add-one-square",
      "median_solve_s": 236,
      "p90_solve_s": 1892,
      "run_success_rate": 0.3333,
      "runs": 3,
      "status": "proved",
      "successes": 1,
      "successes_per_recorded_hour": 1.6,
      "total_solve_s": 2250
    },
    {
      "attempt_yield": 0.0,
      "attempts": 2,
      "difficulty": 2,
      "failed_attempts": 2,
      "failures": 2,
      "goal": "lcm-self-succ",
      "median_solve_s": 1076,
      "p90_solve_s": 1897,
      "run_success_rate": 0.0,
      "runs": 2,
      "status": "open",
      "successes": 0,
      "successes_per_recorded_hour": 0.0,
      "total_solve_s": 2152
    },
    {
      "attempt_yield": 0.0,
      "attempts": 2,
      "difficulty": 2,
      "failed_attempts": 2,
      "failures": 2,
      "goal": "forty-two-dvd-pow-seven-sub-self",
      "median_solve_s": 1062,
      "p90_solve_s": 1881,
      "run_success_rate": 0.0,
      "runs": 2,
      "status": "open",
      "successes": 0,
      "successes_per_recorded_hour": 0.0,
      "total_solve_s": 2125
    },
    {
      "attempt_yield": 0.0,
      "attempts": 2,
      "difficulty": 4,
      "failed_attempts": 2,
      "failures": 2,
      "goal": "no-nat-sq-eq-two-mul-sq",
      "median_solve_s": 1052,
      "p90_solve_s": 1902,
      "run_success_rate": 0.0,
      "runs": 2,
      "status": "open",
      "successes": 0,
      "successes_per_recorded_hour": 0.0,
      "total_solve_s": 2105
    },
    {
      "attempt_yield": 0.3333,
      "attempts": 3,
      "difficulty": 1,
      "failed_attempts": 2,
      "failures": 0,
      "goal": "sq-add-sq-eq-three-mul-sq-s2",
      "median_solve_s": 2081,
      "p90_solve_s": 2081,
      "run_success_rate": 1.0,
      "runs": 1,
      "status": "proved",
      "successes": 1,
      "successes_per_recorded_hour": 1.73,
      "total_solve_s": 2081
    },
    {
      "attempt_yield": 0.0,
      "attempts": 2,
      "difficulty": 3,
      "failed_attempts": 2,
      "failures": 2,
      "goal": "no-int-sq-eq-eight-mul-add-three",
      "median_solve_s": 859,
      "p90_solve_s": 1566,
      "run_success_rate": 0.0,
      "runs": 2,
      "status": "open",
      "successes": 0,
      "successes_per_recorded_hour": 0.0,
      "total_solve_s": 1719
    },
    {
      "attempt_yield": 0.3333,
      "attempts": 3,
      "difficulty": 3,
      "failed_attempts": 2,
      "failures": 0,
      "goal": "pow-four-add-sq-add-one-not-prime",
      "median_solve_s": 1458,
      "p90_solve_s": 1458,
      "run_success_rate": 1.0,
      "runs": 1,
      "status": "proved",
      "successes": 1,
      "successes_per_recorded_hour": 2.469,
      "total_solve_s": 1458
    },
    {
      "attempt_yield": 0.0,
      "attempts": 2,
      "difficulty": 2,
      "failed_attempts": 2,
      "failures": 2,
      "goal": "fib-add-four-eq-three-mul-fib-add-two-sub-fib",
      "median_solve_s": 340,
      "p90_solve_s": 448,
      "run_success_rate": 0.0,
      "runs": 2,
      "status": "open",
      "successes": 0,
      "successes_per_recorded_hour": 0.0,
      "total_solve_s": 680
    },
    {
      "attempt_yield": 0.3333,
      "attempts": 3,
      "difficulty": 1,
      "failed_attempts": 2,
      "failures": 1,
      "goal": "no-nat-sq-eq-two-mul-sq-s3",
      "median_solve_s": 333,
      "p90_solve_s": 340,
      "run_success_rate": 0.5,
      "runs": 2,
      "status": "proved",
      "successes": 1,
      "successes_per_recorded_hour": 5.405,
      "total_solve_s": 666
    },
    {
      "attempt_yield": 0.0,
      "attempts": 2,
      "difficulty": 2,
      "failed_attempts": 2,
      "failures": 2,
      "goal": "sum-four-pow-ge-sq-prod",
      "median_solve_s": 264,
      "p90_solve_s": 398,
      "run_success_rate": 0.0,
      "runs": 2,
      "status": "proved",
      "successes": 0,
      "successes_per_recorded_hour": 0.0,
      "total_solve_s": 529
    },
    {
      "attempt_yield": 0.0,
      "attempts": 2,
      "difficulty": 1,
      "failed_attempts": 2,
      "failures": 2,
      "goal": "four-var-qm-am-s2",
      "median_solve_s": 257,
      "p90_solve_s": 277,
      "run_success_rate": 0.0,
      "runs": 2,
      "status": "open",
      "successes": 0,
      "successes_per_recorded_hour": 0.0,
      "total_solve_s": 515
    },
    {
      "attempt_yield": 0.0,
      "attempts": 2,
      "difficulty": 1,
      "failed_attempts": 2,
      "failures": 2,
      "goal": "am-gm-three-cube-s1",
      "median_solve_s": 254,
      "p90_solve_s": 303,
      "run_success_rate": 0.0,
      "runs": 2,
      "status": "proved",
      "successes": 0,
      "successes_per_recorded_hour": 0.0,
      "total_solve_s": 508
    },
    {
      "attempt_yield": 0.3333,
      "attempts": 3,
      "difficulty": 1,
      "failed_attempts": 2,
      "failures": 1,
      "goal": "no-nat-sq-eq-two-mul-sq-s1",
      "median_solve_s": 234,
      "p90_solve_s": 244,
      "run_success_rate": 0.5,
      "runs": 2,
      "status": "proved",
      "successes": 1,
      "successes_per_recorded_hour": 7.676,
      "total_solve_s": 469
    },
    {
      "attempt_yield": 0.3333,
      "attempts": 3,
      "difficulty": 3,
      "failed_attempts": 2,
      "failures": 0,
      "goal": "amgm-four-cross-three-var",
      "median_solve_s": 422,
      "p90_solve_s": 422,
      "run_success_rate": 1.0,
      "runs": 1,
      "status": "proved",
      "successes": 1,
      "successes_per_recorded_hour": 8.531,
      "total_solve_s": 422
    },
    {
      "attempt_yield": 0.0,
      "attempts": 2,
      "difficulty": 1,
      "failed_attempts": 2,
      "failures": 2,
      "goal": "cube-sum-ge-three-prod-s2",
      "median_solve_s": 210,
      "p90_solve_s": 241,
      "run_success_rate": 0.0,
      "runs": 2,
      "status": "open",
      "successes": 0,
      "successes_per_recorded_hour": 0.0,
      "total_solve_s": 420
    },
    {
      "attempt_yield": 0.0,
      "attempts": 2,
      "difficulty": 4,
      "failed_attempts": 2,
      "failures": 2,
      "goal": "sum-range-choose-sq-eq-central",
      "median_solve_s": 198,
      "p90_solve_s": 223,
      "run_success_rate": 0.0,
      "runs": 2,
      "status": "open",
      "successes": 0,
      "successes_per_recorded_hour": 0.0,
      "total_solve_s": 397
    },
    {
      "attempt_yield": 0.0,
      "attempts": 2,
      "difficulty": 1,
      "failed_attempts": 2,
      "failures": 2,
      "goal": "sum-icc-choose-hockey-stick-s3",
      "median_solve_s": 169,
      "p90_solve_s": 185,
      "run_success_rate": 0.0,
      "runs": 2,
      "status": "open",
      "successes": 0,
      "successes_per_recorded_hour": 0.0,
      "total_solve_s": 338
    },
    {
      "attempt_yield": 0.0,
      "attempts": 2,
      "difficulty": 1,
      "failed_attempts": 2,
      "failures": 2,
      "goal": "sum-icc-choose-hockey-stick-s2",
      "median_solve_s": 123,
      "p90_solve_s": 164,
      "run_success_rate": 0.0,
      "runs": 2,
      "status": "open",
      "successes": 0,
      "successes_per_recorded_hour": 0.0,
      "total_solve_s": 246
    },
    {
      "attempt_yield": 0.0,
      "attempts": 1,
      "difficulty": 3,
      "failed_attempts": 1,
      "failures": 1,
      "goal": "sum-range-odd-cubes",
      "median_solve_s": 1967,
      "p90_solve_s": 1967,
      "run_success_rate": 0.0,
      "runs": 1,
      "status": "open",
      "successes": 0,
      "successes_per_recorded_hour": 0.0,
      "total_solve_s": 1967
    },
    {
      "attempt_yield": 0.0,
      "attempts": 1,
      "difficulty": 2,
      "failed_attempts": 1,
      "failures": 1,
      "goal": "coprime-3n1-4n1",
      "median_solve_s": 1961,
      "p90_solve_s": 1961,
      "run_success_rate": 0.0,
      "runs": 1,
      "status": "open",
      "successes": 0,
      "successes_per_recorded_hour": 0.0,
      "total_solve_s": 1961
    },
    {
      "attempt_yield": 0.0,
      "attempts": 1,
      "difficulty": 2,
      "failed_attempts": 1,
      "failures": 1,
      "goal": "cube-mod-seven",
      "median_solve_s": 1953,
      "p90_solve_s": 1953,
      "run_success_rate": 0.0,
      "runs": 1,
      "status": "open",
      "successes": 0,
      "successes_per_recorded_hour": 0.0,
      "total_solve_s": 1953
    },
    {
      "attempt_yield": 0.0,
      "attempts": 1,
      "difficulty": 2,
      "failed_attempts": 1,
      "failures": 1,
      "goal": "sum-sq-add-one-ge-mul-add",
      "median_solve_s": 1932,
      "p90_solve_s": 1932,
      "run_success_rate": 0.0,
      "runs": 1,
      "status": "proved",
      "successes": 0,
      "successes_per_recorded_hour": 0.0,
      "total_solve_s": 1932
    },
    {
      "attempt_yield": 0.0,
      "attempts": 1,
      "difficulty": 2,
      "failed_attempts": 1,
      "failures": 1,
      "goal": "dvd-twentyfour-pow-six-sub-pow-four",
      "median_solve_s": 1922,
      "p90_solve_s": 1922,
      "run_success_rate": 0.0,
      "runs": 1,
      "status": "open",
      "successes": 0,
      "successes_per_recorded_hour": 0.0,
      "total_solve_s": 1922
    },
    {
      "attempt_yield": 0.0,
      "attempts": 1,
      "difficulty": 2,
      "failed_attempts": 1,
      "failures": 1,
      "goal": "recip-succ-lt-recip",
      "median_solve_s": 1891,
      "p90_solve_s": 1891,
      "run_success_rate": 0.0,
      "runs": 1,
      "status": "open",
      "successes": 0,
      "successes_per_recorded_hour": 0.0,
      "total_solve_s": 1891
    },
    {
      "attempt_yield": 0.0,
      "attempts": 1,
      "difficulty": 5,
      "failed_attempts": 1,
      "failures": 1,
      "goal": "realization-determines-counts",
      "median_solve_s": 1888,
      "p90_solve_s": 1888,
      "run_success_rate": 0.0,
      "runs": 1,
      "status": "open",
      "successes": 0,
      "successes_per_recorded_hour": 0.0,
      "total_solve_s": 1888
    },
    {
      "attempt_yield": 0.0,
      "attempts": 1,
      "difficulty": 2,
      "failed_attempts": 1,
      "failures": 1,
      "goal": "dvd-twentyfour-pow-five-sub-pow-three",
      "median_solve_s": 1887,
      "p90_solve_s": 1887,
      "run_success_rate": 0.0,
      "runs": 1,
      "status": "open",
      "successes": 0,
      "successes_per_recorded_hour": 0.0,
      "total_solve_s": 1887
    },
    {
      "attempt_yield": 0.0,
      "attempts": 1,
      "difficulty": 2,
      "failed_attempts": 1,
      "failures": 1,
      "goal": "realization-edge-relation",
      "median_solve_s": 1887,
      "p90_solve_s": 1887,
      "run_success_rate": 0.0,
      "runs": 1,
      "status": "open",
      "successes": 0,
      "successes_per_recorded_hour": 0.0,
      "total_solve_s": 1887
    },
    {
      "attempt_yield": 0.0,
      "attempts": 1,
      "difficulty": 3,
      "failed_attempts": 1,
      "failures": 1,
      "goal": "cyclic-quad-ge-abc-times-sum",
      "median_solve_s": 1883,
      "p90_solve_s": 1883,
      "run_success_rate": 0.0,
      "runs": 1,
      "status": "open",
      "successes": 0,
      "successes_per_recorded_hour": 0.0,
      "total_solve_s": 1883
    },
    {
      "attempt_yield": 0.5,
      "attempts": 2,
      "difficulty": 3,
      "failed_attempts": 1,
      "failures": 0,
      "goal": "euclid-perfect-numbers",
      "median_solve_s": 1103,
      "p90_solve_s": 1103,
      "run_success_rate": 1.0,
      "runs": 1,
      "status": "archived",
      "successes": 1,
      "successes_per_recorded_hour": 3.264,
      "total_solve_s": 1103
    },
    {
      "attempt_yield": 0.5,
      "attempts": 2,
      "difficulty": 1,
      "failed_attempts": 1,
      "failures": 0,
      "goal": "sq-add-sq-eq-three-mul-sq-s3",
      "median_solve_s": 1008,
      "p90_solve_s": 1008,
      "run_success_rate": 1.0,
      "runs": 1,
      "status": "proved",
      "successes": 1,
      "successes_per_recorded_hour": 3.571,
      "total_solve_s": 1008
    },
    {
      "attempt_yield": 0.5,
      "attempts": 2,
      "difficulty": 3,
      "failed_attempts": 1,
      "failures": 1,
      "goal": "cauchy-schwarz-three-term",
      "median_solve_s": 396,
      "p90_solve_s": 537,
      "run_success_rate": 0.5,
      "runs": 2,
      "status": "proved",
      "successes": 1,
      "successes_per_recorded_hour": 4.545,
      "total_solve_s": 792
    },
    {
      "attempt_yield": 0.5,
      "attempts": 2,
      "difficulty": 2,
      "failed_attempts": 1,
      "failures": 1,
      "goal": "sum-four-sq-ge-two-cross",
      "median_solve_s": 385,
      "p90_solve_s": 661,
      "run_success_rate": 0.5,
      "runs": 2,
      "status": "proved",
      "successes": 1,
      "successes_per_recorded_hour": 4.675,
      "total_solve_s": 770
    },
    {
      "attempt_yield": 0.0,
      "attempts": 1,
      "difficulty": 2,
      "failed_attempts": 1,
      "failures": 1,
      "goal": "six-dvd-three-consecutive-int",
      "median_solve_s": 663,
      "p90_solve_s": 663,
      "run_success_rate": 0.0,
      "runs": 1,
      "status": "open",
      "successes": 0,
      "successes_per_recorded_hour": 0.0,
      "total_solve_s": 663
    },
    {
      "attempt_yield": 0.5,
      "attempts": 2,
      "difficulty": 2,
      "failed_attempts": 1,
      "failures": 1,
      "goal": "four-var-cyclic-sos",
      "median_solve_s": 326,
      "p90_solve_s": 328,
      "run_success_rate": 0.5,
      "runs": 2,
      "status": "proved",
      "successes": 1,
      "successes_per_recorded_hour": 5.521,
      "total_solve_s": 652
    },
    {
      "attempt_yield": 0.5,
      "attempts": 2,
      "difficulty": 1,
      "failed_attempts": 1,
      "failures": 1,
      "goal": "no-nat-sq-eq-two-mul-sq-s2",
      "median_solve_s": 299,
      "p90_solve_s": 388,
      "run_success_rate": 0.5,
      "runs": 2,
      "status": "proved",
      "successes": 1,
      "successes_per_recorded_hour": 6.01,
      "total_solve_s": 599
    },
    {
      "attempt_yield": 0.5,
      "attempts": 2,
      "difficulty": 1,
      "failed_attempts": 1,
      "failures": 1,
      "goal": "am-hm-two-var-s2",
      "median_solve_s": 290,
      "p90_solve_s": 375,
      "run_success_rate": 0.5,
      "runs": 2,
      "status": "proved",
      "successes": 1,
      "successes_per_recorded_hour": 6.196,
      "total_solve_s": 581
    },
    {
      "attempt_yield": 0.5,
      "attempts": 2,
      "difficulty": 3,
      "failed_attempts": 1,
      "failures": 0,
      "goal": "one-add-four-b-fourth-not-prime",
      "median_solve_s": 547,
      "p90_solve_s": 547,
      "run_success_rate": 1.0,
      "runs": 1,
      "status": "proved",
      "successes": 1,
      "successes_per_recorded_hour": 6.581,
      "total_solve_s": 547
    },
    {
      "attempt_yield": 0.0,
      "attempts": 1,
      "difficulty": 2,
      "failed_attempts": 1,
      "failures": 1,
      "goal": "dvd-twentyfour-pow-seven-sub-pow-five",
      "median_solve_s": 530,
      "p90_solve_s": 530,
      "run_success_rate": 0.0,
      "runs": 1,
      "status": "open",
      "successes": 0,
      "successes_per_recorded_hour": 0.0,
      "total_solve_s": 530
    },
    {
      "attempt_yield": 0.5,
      "attempts": 2,
      "difficulty": 1,
      "failed_attempts": 1,
      "failures": 1,
      "goal": "nat-sq-lt-two-pow-s2-s1",
      "median_solve_s": 263,
      "p90_solve_s": 293,
      "run_success_rate": 0.5,
      "runs": 2,
      "status": "proved",
      "successes": 1,
      "successes_per_recorded_hour": 6.831,
      "total_solve_s": 527
    },
    {
      "attempt_yield": 0.5,
      "attempts": 2,
      "difficulty": 2,
      "failed_attempts": 1,
      "failures": 1,
      "goal": "constrained-sum-sq-ge-three",
      "median_solve_s": 262,
      "p90_solve_s": 337,
      "run_success_rate": 0.5,
      "runs": 2,
      "status": "proved",
      "successes": 1,
      "successes_per_recorded_hour": 6.857,
      "total_solve_s": 525
    },
    {
      "attempt_yield": 0.5,
      "attempts": 2,
      "difficulty": 1,
      "failed_attempts": 1,
      "failures": 1,
      "goal": "nesbitt-inequality-s4",
      "median_solve_s": 241,
      "p90_solve_s": 258,
      "run_success_rate": 0.5,
      "runs": 2,
      "status": "proved",
      "successes": 1,
      "successes_per_recorded_hour": 7.453,
      "total_solve_s": 483
    },
    {
      "attempt_yield": 0.0,
      "attempts": 1,
      "difficulty": 2,
      "failed_attempts": 1,
      "failures": 1,
      "goal": "weighted-am-gm-cubed",
      "median_solve_s": 458,
      "p90_solve_s": 458,
      "run_success_rate": 0.0,
      "runs": 1,
      "status": "open",
      "successes": 0,
      "successes_per_recorded_hour": 0.0,
      "total_solve_s": 458
    },
    {
      "attempt_yield": 0.5,
      "attempts": 2,
      "difficulty": 1,
      "failed_attempts": 1,
      "failures": 1,
      "goal": "nesbitt-inequality-s3",
      "median_solve_s": 225,
      "p90_solve_s": 231,
      "run_success_rate": 0.5,
      "runs": 2,
      "status": "proved",
      "successes": 1,
      "successes_per_recorded_hour": 8.0,
      "total_solve_s": 450
    },
    {
      "attempt_yield": 0.0,
      "attempts": 1,
      "difficulty": 2,
      "failed_attempts": 1,
      "failures": 1,
      "goal": "dvd-sixty-pow-six-sub-sq",
      "median_solve_s": 429,
      "p90_solve_s": 429,
      "run_success_rate": 0.0,
      "runs": 1,
      "status": "open",
      "successes": 0,
      "successes_per_recorded_hour": 0.0,
      "total_solve_s": 429
    },
    {
      "attempt_yield": 0.0,
      "attempts": 1,
      "difficulty": 2,
      "failed_attempts": 1,
      "failures": 1,
      "goal": "fib-add-five-eq-five-mul-fib-succ-add-three-mul-fib",
      "median_solve_s": 414,
      "p90_solve_s": 414,
      "run_success_rate": 0.0,
      "runs": 1,
      "status": "open",
      "successes": 0,
      "successes_per_recorded_hour": 0.0,
      "total_solve_s": 414
    },
    {
      "attempt_yield": 0.5,
      "attempts": 2,
      "difficulty": 1,
      "failed_attempts": 1,
      "failures": 1,
      "goal": "am-gm-three-cube-s2-s2-s1",
      "median_solve_s": 202,
      "p90_solve_s": 213,
      "run_success_rate": 0.5,
      "runs": 2,
      "status": "proved",
      "successes": 1,
      "successes_per_recorded_hour": 8.889,
      "total_solve_s": 405
    },
    {
      "attempt_yield": 0.0,
      "attempts": 1,
      "difficulty": 2,
      "failed_attempts": 1,
      "failures": 1,
      "goal": "fib-add-six-eq-eight-mul-fib-succ-add-five-mul-fib",
      "median_solve_s": 400,
      "p90_solve_s": 400,
      "run_success_rate": 0.0,
      "runs": 1,
      "status": "open",
      "successes": 0,
      "successes_per_recorded_hour": 0.0,
      "total_solve_s": 400
    },
    {
      "attempt_yield": 0.0,
      "attempts": 1,
      "difficulty": 2,
      "failed_attempts": 1,
      "failures": 1,
      "goal": "fib-add-three-eq-two-mul-fib-succ-add-fib",
      "median_solve_s": 394,
      "p90_solve_s": 394,
      "run_success_rate": 0.0,
      "runs": 1,
      "status": "open",
      "successes": 0,
      "successes_per_recorded_hour": 0.0,
      "total_solve_s": 394
    },
    {
      "attempt_yield": 0.0,
      "attempts": 1,
      "difficulty": 2,
      "failed_attempts": 1,
      "failures": 1,
      "goal": "square-of-sum-ge-three-pairwise",
      "median_solve_s": 390,
      "p90_solve_s": 390,
      "run_success_rate": 0.0,
      "runs": 1,
      "status": "open",
      "successes": 0,
      "successes_per_recorded_hour": 0.0,
      "total_solve_s": 390
    },
    {
      "attempt_yield": 0.0,
      "attempts": 1,
      "difficulty": 3,
      "failed_attempts": 1,
      "failures": 1,
      "goal": "gcd-consec-odd-eq-one",
      "median_solve_s": 371,
      "p90_solve_s": 371,
      "run_success_rate": 0.0,
      "runs": 1,
      "status": "open",
      "successes": 0,
      "successes_per_recorded_hour": 0.0,
      "total_solve_s": 371
    },
    {
      "attempt_yield": 0.5,
      "attempts": 2,
      "difficulty": 2,
      "failed_attempts": 1,
      "failures": 0,
      "goal": "odd-fourth-power-mod-sixteen",
      "median_solve_s": 344,
      "p90_solve_s": 344,
      "run_success_rate": 1.0,
      "runs": 1,
      "status": "archived",
      "successes": 1,
      "successes_per_recorded_hour": 10.465,
      "total_solve_s": 344
    },
    {
      "attempt_yield": 0.0,
      "attempts": 1,
      "difficulty": 2,
      "failed_attempts": 1,
      "failures": 1,
      "goal": "bezout-eleven-thirteen-eq-one",
      "median_solve_s": 290,
      "p90_solve_s": 290,
      "run_success_rate": 0.0,
      "runs": 1,
      "status": "open",
      "successes": 0,
      "successes_per_recorded_hour": 0.0,
      "total_solve_s": 290
    },
    {
      "attempt_yield": 0.0,
      "attempts": 1,
      "difficulty": 2,
      "failed_attempts": 1,
      "failures": 1,
      "goal": "product-le-quarter-of-sum-one",
      "median_solve_s": 281,
      "p90_solve_s": 281,
      "run_success_rate": 0.0,
      "runs": 1,
      "status": "proved",
      "successes": 0,
      "successes_per_recorded_hour": 0.0,
      "total_solve_s": 281
    },
    {
      "attempt_yield": 0.0,
      "attempts": 1,
      "difficulty": 2,
      "failed_attempts": 1,
      "failures": 1,
      "goal": "six-dvd-pow-three-sub-self",
      "median_solve_s": 278,
      "p90_solve_s": 278,
      "run_success_rate": 0.0,
      "runs": 1,
      "status": "open",
      "successes": 0,
      "successes_per_recorded_hour": 0.0,
      "total_solve_s": 278
    },
    {
      "attempt_yield": 0.0,
      "attempts": 1,
      "difficulty": 2,
      "failed_attempts": 1,
      "failures": 1,
      "goal": "one-add-two-x-le-sq",
      "median_solve_s": 259,
      "p90_solve_s": 259,
      "run_success_rate": 0.0,
      "runs": 1,
      "status": "proved",
      "successes": 0,
      "successes_per_recorded_hour": 0.0,
      "total_solve_s": 259
    },
    {
      "attempt_yield": 0.0,
      "attempts": 1,
      "difficulty": 3,
      "failed_attempts": 1,
      "failures": 1,
      "goal": "coprime-succ-sq-add",
      "median_solve_s": 257,
      "p90_solve_s": 257,
      "run_success_rate": 0.0,
      "runs": 1,
      "status": "open",
      "successes": 0,
      "successes_per_recorded_hour": 0.0,
      "total_solve_s": 257
    },
    {
      "attempt_yield": 0.0,
      "attempts": 1,
      "difficulty": 2,
      "failed_attempts": 1,
      "failures": 1,
      "goal": "coprime-n-cube-add-one",
      "median_solve_s": 240,
      "p90_solve_s": 240,
      "run_success_rate": 0.0,
      "runs": 1,
      "status": "open",
      "successes": 0,
      "successes_per_recorded_hour": 0.0,
      "total_solve_s": 240
    },
    {
      "attempt_yield": 0.0,
      "attempts": 1,
      "difficulty": 2,
      "failed_attempts": 1,
      "failures": 1,
      "goal": "sq-sum-le-two-mul-sum-sq",
      "median_solve_s": 238,
      "p90_solve_s": 238,
      "run_success_rate": 0.0,
      "runs": 1,
      "status": "proved",
      "successes": 0,
      "successes_per_recorded_hour": 0.0,
      "total_solve_s": 238
    },
    {
      "attempt_yield": 0.0,
      "attempts": 1,
      "difficulty": 2,
      "failed_attempts": 1,
      "failures": 1,
      "goal": "sq-lt-cube-of-one-lt",
      "median_solve_s": 231,
      "p90_solve_s": 231,
      "run_success_rate": 0.0,
      "runs": 1,
      "status": "proved",
      "successes": 0,
      "successes_per_recorded_hour": 0.0,
      "total_solve_s": 231
    },
    {
      "attempt_yield": 0.0,
      "attempts": 1,
      "difficulty": 1,
      "failed_attempts": 1,
      "failures": 1,
      "goal": "nat-sq-lt-two-pow-s2-s2",
      "median_solve_s": 230,
      "p90_solve_s": 230,
      "run_success_rate": 0.0,
      "runs": 1,
      "status": "proved",
      "successes": 0,
      "successes_per_recorded_hour": 0.0,
      "total_solve_s": 230
    },
    {
      "attempt_yield": 0.0,
      "attempts": 1,
      "difficulty": 4,
      "failed_attempts": 1,
      "failures": 1,
      "goal": "realization-edge-in-set",
      "median_solve_s": 225,
      "p90_solve_s": 225,
      "run_success_rate": 0.0,
      "runs": 1,
      "status": "open",
      "successes": 0,
      "successes_per_recorded_hour": 0.0,
      "total_solve_s": 225
    },
    {
      "attempt_yield": 0.0,
      "attempts": 1,
      "difficulty": 2,
      "failed_attempts": 1,
      "failures": 1,
      "goal": "gcd-n1-n4-dvd-three",
      "median_solve_s": 222,
      "p90_solve_s": 222,
      "run_success_rate": 0.0,
      "runs": 1,
      "status": "open",
      "successes": 0,
      "successes_per_recorded_hour": 0.0,
      "total_solve_s": 222
    },
    {
      "attempt_yield": 0.0,
      "attempts": 1,
      "difficulty": 3,
      "failed_attempts": 1,
      "failures": 1,
      "goal": "platonic-pairs-realizable",
      "median_solve_s": 198,
      "p90_solve_s": 198,
      "run_success_rate": 0.0,
      "runs": 1,
      "status": "open",
      "successes": 0,
      "successes_per_recorded_hour": 0.0,
      "total_solve_s": 198
    },
    {
      "attempt_yield": 0.0,
      "attempts": 1,
      "difficulty": 3,
      "failed_attempts": 1,
      "failures": 1,
      "goal": "sum-range-triangular-eq-tetrahedral",
      "median_solve_s": 198,
      "p90_solve_s": 198,
      "run_success_rate": 0.0,
      "runs": 1,
      "status": "open",
      "successes": 0,
      "successes_per_recorded_hour": 0.0,
      "total_solve_s": 198
    },
    {
      "attempt_yield": 0.0,
      "attempts": 1,
      "difficulty": 2,
      "failed_attempts": 1,
      "failures": 1,
      "goal": "qm-am-three-var",
      "median_solve_s": 184,
      "p90_solve_s": 184,
      "run_success_rate": 0.0,
      "runs": 1,
      "status": "proved",
      "successes": 0,
      "successes_per_recorded_hour": 0.0,
      "total_solve_s": 184
    },
    {
      "attempt_yield": 0.0,
      "attempts": 1,
      "difficulty": 2,
      "failed_attempts": 1,
      "failures": 1,
      "goal": "quartic-ge-sq-prod",
      "median_solve_s": 183,
      "p90_solve_s": 183,
      "run_success_rate": 0.0,
      "runs": 1,
      "status": "proved",
      "successes": 0,
      "successes_per_recorded_hour": 0.0,
      "total_solve_s": 183
    },
    {
      "attempt_yield": 0.0,
      "attempts": 1,
      "difficulty": 2,
      "failed_attempts": 1,
      "failures": 1,
      "goal": "quartic-ge-cross",
      "median_solve_s": 181,
      "p90_solve_s": 181,
      "run_success_rate": 0.0,
      "runs": 1,
      "status": "proved",
      "successes": 0,
      "successes_per_recorded_hour": 0.0,
      "total_solve_s": 181
    },
    {
      "attempt_yield": 0.0,
      "attempts": 1,
      "difficulty": 2,
      "failed_attempts": 1,
      "failures": 1,
      "goal": "cube-mod-four",
      "median_solve_s": 180,
      "p90_solve_s": 180,
      "run_success_rate": 0.0,
      "runs": 1,
      "status": "open",
      "successes": 0,
      "successes_per_recorded_hour": 0.0,
      "total_solve_s": 180
    },
    {
      "attempt_yield": 0.0,
      "attempts": 1,
      "difficulty": 1,
      "failed_attempts": 1,
      "failures": 1,
      "goal": "nat-sq-lt-two-pow-s2-s3",
      "median_solve_s": 178,
      "p90_solve_s": 178,
      "run_success_rate": 0.0,
      "runs": 1,
      "status": "proved",
      "successes": 0,
      "successes_per_recorded_hour": 0.0,
      "total_solve_s": 178
    },
    {
      "attempt_yield": 0.0,
      "attempts": 1,
      "difficulty": 4,
      "failed_attempts": 1,
      "failures": 1,
      "goal": "nesbitt-inequality",
      "median_solve_s": 163,
      "p90_solve_s": 163,
      "run_success_rate": 0.0,
      "runs": 1,
      "status": "blocked",
      "successes": 0,
      "successes_per_recorded_hour": 0.0,
      "total_solve_s": 163
    },
    {
      "attempt_yield": 0.0,
      "attempts": 1,
      "difficulty": 3,
      "failed_attempts": 1,
      "failures": 1,
      "goal": "sum-icc-choose-hockey-stick",
      "median_solve_s": 160,
      "p90_solve_s": 160,
      "run_success_rate": 0.0,
      "runs": 1,
      "status": "blocked",
      "successes": 0,
      "successes_per_recorded_hour": 0.0,
      "total_solve_s": 160
    },
    {
      "attempt_yield": 0.0,
      "attempts": 1,
      "difficulty": 2,
      "failed_attempts": 1,
      "failures": 1,
      "goal": "gcd-self-add-dvd",
      "median_solve_s": 157,
      "p90_solve_s": 157,
      "run_success_rate": 0.0,
      "runs": 1,
      "status": "open",
      "successes": 0,
      "successes_per_recorded_hour": 0.0,
      "total_solve_s": 157
    },
    {
      "attempt_yield": 0.0,
      "attempts": 1,
      "difficulty": 3,
      "failed_attempts": 1,
      "failures": 1,
      "goal": "nat-sq-lt-two-pow",
      "median_solve_s": 130,
      "p90_solve_s": 130,
      "run_success_rate": 0.0,
      "runs": 1,
      "status": "proved",
      "successes": 0,
      "successes_per_recorded_hour": 0.0,
      "total_solve_s": 130
    },
    {
      "attempt_yield": 0.0,
      "attempts": 1,
      "difficulty": 2,
      "failed_attempts": 1,
      "failures": 1,
      "goal": "one-add-three-x-le-cube",
      "median_solve_s": 122,
      "p90_solve_s": 122,
      "run_success_rate": 0.0,
      "runs": 1,
      "status": "proved",
      "successes": 0,
      "successes_per_recorded_hour": 0.0,
      "total_solve_s": 122
    },
    {
      "attempt_yield": 1.0,
      "attempts": 1,
      "difficulty": 1,
      "failed_attempts": 0,
      "failures": 0,
      "goal": "sum-four-pow-ge-sq-prod-s2",
      "median_solve_s": 1061,
      "p90_solve_s": 1061,
      "run_success_rate": 1.0,
      "runs": 1,
      "status": "proved",
      "successes": 1,
      "successes_per_recorded_hour": 3.393,
      "total_solve_s": 1061
    },
    {
      "attempt_yield": 1.0,
      "attempts": 1,
      "difficulty": 3,
      "failed_attempts": 0,
      "failures": 0,
      "goal": "gcd-lin-3n2-5n3",
      "median_solve_s": 938,
      "p90_solve_s": 938,
      "run_success_rate": 1.0,
      "runs": 1,
      "status": "proved",
      "successes": 1,
      "successes_per_recorded_hour": 3.838,
      "total_solve_s": 938
    },
    {
      "attempt_yield": 1.0,
      "attempts": 1,
      "difficulty": 1,
      "failed_attempts": 0,
      "failures": 0,
      "goal": "sum-four-pow-ge-sq-prod-s1",
      "median_solve_s": 718,
      "p90_solve_s": 718,
      "run_success_rate": 1.0,
      "runs": 1,
      "status": "proved",
      "successes": 1,
      "successes_per_recorded_hour": 5.014,
      "total_solve_s": 718
    },
    {
      "attempt_yield": 1.0,
      "attempts": 1,
      "difficulty": 2,
      "failed_attempts": 0,
      "failures": 0,
      "goal": "sum-sq-add-three-ge-two-sum",
      "median_solve_s": 619,
      "p90_solve_s": 619,
      "run_success_rate": 1.0,
      "runs": 1,
      "status": "proved",
      "successes": 1,
      "successes_per_recorded_hour": 5.816,
      "total_solve_s": 619
    },
    {
      "attempt_yield": 1.0,
      "attempts": 1,
      "difficulty": 3,
      "failed_attempts": 0,
      "failures": 0,
      "goal": "sum-range-pow-four-triangular-form",
      "median_solve_s": 598,
      "p90_solve_s": 598,
      "run_success_rate": 1.0,
      "runs": 1,
      "status": "archived",
      "successes": 1,
      "successes_per_recorded_hour": 6.02,
      "total_solve_s": 598
    },
    {
      "attempt_yield": 1.0,
      "attempts": 1,
      "difficulty": 1,
      "failed_attempts": 0,
      "failures": 0,
      "goal": "am-hm-two-var-s1",
      "median_solve_s": 569,
      "p90_solve_s": 569,
      "run_success_rate": 1.0,
      "runs": 1,
      "status": "proved",
      "successes": 1,
      "successes_per_recorded_hour": 6.327,
      "total_solve_s": 569
    },
    {
      "attempt_yield": 1.0,
      "attempts": 1,
      "difficulty": 4,
      "failed_attempts": 0,
      "failures": 0,
      "goal": "sum-range-pow-seven-closed-form",
      "median_solve_s": 569,
      "p90_solve_s": 569,
      "run_success_rate": 1.0,
      "runs": 1,
      "status": "archived",
      "successes": 1,
      "successes_per_recorded_hour": 6.327,
      "total_solve_s": 569
    },
    {
      "attempt_yield": 1.0,
      "attempts": 1,
      "difficulty": 3,
      "failed_attempts": 0,
      "failures": 0,
      "goal": "sum-range-cube-mul-choose",
      "median_solve_s": 556,
      "p90_solve_s": 556,
      "run_success_rate": 1.0,
      "runs": 1,
      "status": "proved",
      "successes": 1,
      "successes_per_recorded_hour": 6.475,
      "total_solve_s": 556
    },
    {
      "attempt_yield": 1.0,
      "attempts": 1,
      "difficulty": 1,
      "failed_attempts": 0,
      "failures": 0,
      "goal": "four-var-qm-am-s3",
      "median_solve_s": 542,
      "p90_solve_s": 542,
      "run_success_rate": 1.0,
      "runs": 1,
      "status": "proved",
      "successes": 1,
      "successes_per_recorded_hour": 6.642,
      "total_solve_s": 542
    },
    {
      "attempt_yield": 1.0,
      "attempts": 1,
      "difficulty": 1,
      "failed_attempts": 0,
      "failures": 0,
      "goal": "sum-four-sq-ge-two-cross-s2",
      "median_solve_s": 487,
      "p90_solve_s": 487,
      "run_success_rate": 1.0,
      "runs": 1,
      "status": "proved",
      "successes": 1,
      "successes_per_recorded_hour": 7.392,
      "total_solve_s": 487
    },
    {
      "attempt_yield": 1.0,
      "attempts": 1,
      "difficulty": 1,
      "failed_attempts": 0,
      "failures": 0,
      "goal": "sum-four-sq-ge-two-cross-s1",
      "median_solve_s": 463,
      "p90_solve_s": 463,
      "run_success_rate": 1.0,
      "runs": 1,
      "status": "proved",
      "successes": 1,
      "successes_per_recorded_hour": 7.775,
      "total_solve_s": 463
    },
    {
      "attempt_yield": 1.0,
      "attempts": 1,
      "difficulty": 2,
      "failed_attempts": 0,
      "failures": 0,
      "goal": "four-mul-prod-le-sq-sum",
      "median_solve_s": 440,
      "p90_solve_s": 440,
      "run_success_rate": 1.0,
      "runs": 1,
      "status": "proved",
      "successes": 1,
      "successes_per_recorded_hour": 8.182,
      "total_solve_s": 440
    },
    {
      "attempt_yield": 1.0,
      "attempts": 1,
      "difficulty": 1,
      "failed_attempts": 0,
      "failures": 0,
      "goal": "sq-add-sq-eq-three-mul-sq-s1",
      "median_solve_s": 420,
      "p90_solve_s": 420,
      "run_success_rate": 1.0,
      "runs": 1,
      "status": "proved",
      "successes": 1,
      "successes_per_recorded_hour": 8.571,
      "total_solve_s": 420
    },
    {
      "attempt_yield": 1.0,
      "attempts": 1,
      "difficulty": 3,
      "failed_attempts": 0,
      "failures": 0,
      "goal": "sum-range-pow-six-closed-form",
      "median_solve_s": 417,
      "p90_solve_s": 417,
      "run_success_rate": 1.0,
      "runs": 1,
      "status": "proved",
      "successes": 1,
      "successes_per_recorded_hour": 8.633,
      "total_solve_s": 417
    },
    {
      "attempt_yield": 1.0,
      "attempts": 1,
      "difficulty": 1,
      "failed_attempts": 0,
      "failures": 0,
      "goal": "cube-sum-ge-three-prod-s3",
      "median_solve_s": 406,
      "p90_solve_s": 406,
      "run_success_rate": 1.0,
      "runs": 1,
      "status": "proved",
      "successes": 1,
      "successes_per_recorded_hour": 8.867,
      "total_solve_s": 406
    },
    {
      "attempt_yield": 1.0,
      "attempts": 1,
      "difficulty": 3,
      "failed_attempts": 0,
      "failures": 0,
      "goal": "prod-range-one-add-inv",
      "median_solve_s": 393,
      "p90_solve_s": 393,
      "run_success_rate": 1.0,
      "runs": 1,
      "status": "proved",
      "successes": 1,
      "successes_per_recorded_hour": 9.16,
      "total_solve_s": 393
    },
    {
      "attempt_yield": 1.0,
      "attempts": 1,
      "difficulty": 3,
      "failed_attempts": 0,
      "failures": 0,
      "goal": "cube-mod-thirteen-mem",
      "median_solve_s": 391,
      "p90_solve_s": 391,
      "run_success_rate": 1.0,
      "runs": 1,
      "status": "proved",
      "successes": 1,
      "successes_per_recorded_hour": 9.207,
      "total_solve_s": 391
    },
    {
      "attempt_yield": 1.0,
      "attempts": 1,
      "difficulty": 2,
      "failed_attempts": 0,
      "failures": 0,
      "goal": "coprime-n-sq-n-add-one",
      "median_solve_s": 383,
      "p90_solve_s": 383,
      "run_success_rate": 1.0,
      "runs": 1,
      "status": "proved",
      "successes": 1,
      "successes_per_recorded_hour": 9.399,
      "total_solve_s": 383
    },
    {
      "attempt_yield": 1.0,
      "attempts": 1,
      "difficulty": 4,
      "failed_attempts": 0,
      "failures": 0,
      "goal": "sum-range-pow-five-add-pow-seven",
      "median_solve_s": 342,
      "p90_solve_s": 342,
      "run_success_rate": 1.0,
      "runs": 1,
      "status": "archived",
      "successes": 1,
      "successes_per_recorded_hour": 10.526,
      "total_solve_s": 342
    },
    {
      "attempt_yield": 1.0,
      "attempts": 1,
      "difficulty": 3,
      "failed_attempts": 0,
      "failures": 0,
      "goal": "fourth-power-mod-eight-mem",
      "median_solve_s": 326,
      "p90_solve_s": 326,
      "run_success_rate": 1.0,
      "runs": 1,
      "status": "proved",
      "successes": 1,
      "successes_per_recorded_hour": 11.043,
      "total_solve_s": 326
    },
    {
      "attempt_yield": 1.0,
      "attempts": 1,
      "difficulty": 2,
      "failed_attempts": 0,
      "failures": 0,
      "goal": "two-abs-le-sq-add-one",
      "median_solve_s": 325,
      "p90_solve_s": 325,
      "run_success_rate": 1.0,
      "runs": 1,
      "status": "proved",
      "successes": 1,
      "successes_per_recorded_hour": 11.077,
      "total_solve_s": 325
    },
    {
      "attempt_yield": 1.0,
      "attempts": 1,
      "difficulty": 1,
      "failed_attempts": 0,
      "failures": 0,
      "goal": "am-gm-three-cube-s2-s2-s2",
      "median_solve_s": 309,
      "p90_solve_s": 309,
      "run_success_rate": 1.0,
      "runs": 1,
      "status": "proved",
      "successes": 1,
      "successes_per_recorded_hour": 11.65,
      "total_solve_s": 309
    },
    {
      "attempt_yield": 1.0,
      "attempts": 1,
      "difficulty": 2,
      "failed_attempts": 0,
      "failures": 0,
      "goal": "twenty-four-dvd-four-consecutive",
      "median_solve_s": 299,
      "p90_solve_s": 299,
      "run_success_rate": 1.0,
      "runs": 1,
      "status": "proved",
      "successes": 1,
      "successes_per_recorded_hour": 12.04,
      "total_solve_s": 299
    },
    {
      "attempt_yield": 1.0,
      "attempts": 1,
      "difficulty": 2,
      "failed_attempts": 0,
      "failures": 0,
      "goal": "eight-dvd-consecutive-odd-sq-diff",
      "median_solve_s": 297,
      "p90_solve_s": 297,
      "run_success_rate": 1.0,
      "runs": 1,
      "status": "proved",
      "successes": 1,
      "successes_per_recorded_hour": 12.121,
      "total_solve_s": 297
    },
    {
      "attempt_yield": 1.0,
      "attempts": 1,
      "difficulty": 1,
      "failed_attempts": 0,
      "failures": 0,
      "goal": "four-consecutive-product-add-one-square-s1",
      "median_solve_s": 297,
      "p90_solve_s": 297,
      "run_success_rate": 1.0,
      "runs": 1,
      "status": "proved",
      "successes": 1,
      "successes_per_recorded_hour": 12.121,
      "total_solve_s": 297
    },
    {
      "attempt_yield": 1.0,
      "attempts": 1,
      "difficulty": 3,
      "failed_attempts": 0,
      "failures": 0,
      "goal": "sum-range-fall-mul-choose",
      "median_solve_s": 295,
      "p90_solve_s": 295,
      "run_success_rate": 1.0,
      "runs": 1,
      "status": "proved",
      "successes": 1,
      "successes_per_recorded_hour": 12.203,
      "total_solve_s": 295
    },
    {
      "attempt_yield": 1.0,
      "attempts": 1,
      "difficulty": 3,
      "failed_attempts": 0,
      "failures": 0,
      "goal": "sum-range-pow-five-faulhaber-triangular",
      "median_solve_s": 292,
      "p90_solve_s": 292,
      "run_success_rate": 1.0,
      "runs": 1,
      "status": "archived",
      "successes": 1,
      "successes_per_recorded_hour": 12.329,
      "total_solve_s": 292
    },
    {
      "attempt_yield": 1.0,
      "attempts": 1,
      "difficulty": 3,
      "failed_attempts": 0,
      "failures": 0,
      "goal": "fourth-power-mod-thirteen-mem",
      "median_solve_s": 290,
      "p90_solve_s": 290,
      "run_success_rate": 1.0,
      "runs": 1,
      "status": "proved",
      "successes": 1,
      "successes_per_recorded_hour": 12.414,
      "total_solve_s": 290
    },
    {
      "attempt_yield": 1.0,
      "attempts": 1,
      "difficulty": 4,
      "failed_attempts": 0,
      "failures": 0,
      "goal": "prime-fourth-power-mod-240",
      "median_solve_s": 287,
      "p90_solve_s": 287,
      "run_success_rate": 1.0,
      "runs": 1,
      "status": "archived",
      "successes": 1,
      "successes_per_recorded_hour": 12.544,
      "total_solve_s": 287
    },
    {
      "attempt_yield": 1.0,
      "attempts": 1,
      "difficulty": 2,
      "failed_attempts": 0,
      "failures": 0,
      "goal": "twelve-dvd-pow-four-sub-sq",
      "median_solve_s": 285,
      "p90_solve_s": 285,
      "run_success_rate": 1.0,
      "runs": 1,
      "status": "proved",
      "successes": 1,
      "successes_per_recorded_hour": 12.632,
      "total_solve_s": 285
    },
    {
      "attempt_yield": 1.0,
      "attempts": 1,
      "difficulty": 3,
      "failed_attempts": 0,
      "failures": 0,
      "goal": "coprime-2n1-n1",
      "median_solve_s": 262,
      "p90_solve_s": 262,
      "run_success_rate": 1.0,
      "runs": 1,
      "status": "proved",
      "successes": 1,
      "successes_per_recorded_hour": 13.74,
      "total_solve_s": 262
    },
    {
      "attempt_yield": 1.0,
      "attempts": 1,
      "difficulty": 1,
      "failed_attempts": 0,
      "failures": 0,
      "goal": "am-hm-two-var-s3",
      "median_solve_s": 259,
      "p90_solve_s": 259,
      "run_success_rate": 1.0,
      "runs": 1,
      "status": "proved",
      "successes": 1,
      "successes_per_recorded_hour": 13.9,
      "total_solve_s": 259
    },
    {
      "attempt_yield": 1.0,
      "attempts": 1,
      "difficulty": 1,
      "failed_attempts": 0,
      "failures": 0,
      "goal": "four-consecutive-product-add-one-square-s2",
      "median_solve_s": 257,
      "p90_solve_s": 257,
      "run_success_rate": 1.0,
      "runs": 1,
      "status": "proved",
      "successes": 1,
      "successes_per_recorded_hour": 14.008,
      "total_solve_s": 257
    },
    {
      "attempt_yield": 1.0,
      "attempts": 1,
      "difficulty": 2,
      "failed_attempts": 0,
      "failures": 0,
      "goal": "consecutive-triangular-eq-square",
      "median_solve_s": 256,
      "p90_solve_s": 256,
      "run_success_rate": 1.0,
      "runs": 1,
      "status": "proved",
      "successes": 1,
      "successes_per_recorded_hour": 14.062,
      "total_solve_s": 256
    },
    {
      "attempt_yield": 1.0,
      "attempts": 1,
      "difficulty": 1,
      "failed_attempts": 0,
      "failures": 0,
      "goal": "nat-sq-lt-two-pow-s1",
      "median_solve_s": 255,
      "p90_solve_s": 255,
      "run_success_rate": 1.0,
      "runs": 1,
      "status": "proved",
      "successes": 1,
      "successes_per_recorded_hour": 14.118,
      "total_solve_s": 255
    },
    {
      "attempt_yield": 1.0,
      "attempts": 1,
      "difficulty": 2,
      "failed_attempts": 0,
      "failures": 0,
      "goal": "cube-mod-nine",
      "median_solve_s": 249,
      "p90_solve_s": 249,
      "run_success_rate": 1.0,
      "runs": 1,
      "status": "proved",
      "successes": 1,
      "successes_per_recorded_hour": 14.458,
      "total_solve_s": 249
    },
    {
      "attempt_yield": 1.0,
      "attempts": 1,
      "difficulty": 2,
      "failed_attempts": 0,
      "failures": 0,
      "goal": "eight-triangular-add-one-eq-odd-sq",
      "median_solve_s": 238,
      "p90_solve_s": 238,
      "run_success_rate": 1.0,
      "runs": 1,
      "status": "proved",
      "successes": 1,
      "successes_per_recorded_hour": 15.126,
      "total_solve_s": 238
    },
    {
      "attempt_yield": 1.0,
      "attempts": 1,
      "difficulty": 2,
      "failed_attempts": 0,
      "failures": 0,
      "goal": "thirty-dvd-pow-five-sub-self",
      "median_solve_s": 230,
      "p90_solve_s": 230,
      "run_success_rate": 1.0,
      "runs": 1,
      "status": "proved",
      "successes": 1,
      "successes_per_recorded_hour": 15.652,
      "total_solve_s": 230
    },
    {
      "attempt_yield": 1.0,
      "attempts": 1,
      "difficulty": 2,
      "failed_attempts": 0,
      "failures": 0,
      "goal": "fifth-power-mod-eleven",
      "median_solve_s": 222,
      "p90_solve_s": 222,
      "run_success_rate": 1.0,
      "runs": 1,
      "status": "proved",
      "successes": 1,
      "successes_per_recorded_hour": 16.216,
      "total_solve_s": 222
    },
    {
      "attempt_yield": 1.0,
      "attempts": 1,
      "difficulty": 1,
      "failed_attempts": 0,
      "failures": 0,
      "goal": "am-gm-three-cube-s2-s1",
      "median_solve_s": 219,
      "p90_solve_s": 219,
      "run_success_rate": 1.0,
      "runs": 1,
      "status": "proved",
      "successes": 1,
      "successes_per_recorded_hour": 16.438,
      "total_solve_s": 219
    },
    {
      "attempt_yield": 1.0,
      "attempts": 1,
      "difficulty": 3,
      "failed_attempts": 0,
      "failures": 0,
      "goal": "four-not-dvd-sq-add-two",
      "median_solve_s": 211,
      "p90_solve_s": 211,
      "run_success_rate": 1.0,
      "runs": 1,
      "status": "proved",
      "successes": 1,
      "successes_per_recorded_hour": 17.062,
      "total_solve_s": 211
    },
    {
      "attempt_yield": 1.0,
      "attempts": 1,
      "difficulty": 2,
      "failed_attempts": 0,
      "failures": 0,
      "goal": "pow-four-add-sq-add-one-factor",
      "median_solve_s": 202,
      "p90_solve_s": 202,
      "run_success_rate": 1.0,
      "runs": 1,
      "status": "proved",
      "successes": 1,
      "successes_per_recorded_hour": 17.822,
      "total_solve_s": 202
    },
    {
      "attempt_yield": 1.0,
      "attempts": 1,
      "difficulty": 2,
      "failed_attempts": 0,
      "failures": 0,
      "goal": "two-abs-mul-le-sq-add-sq",
      "median_solve_s": 199,
      "p90_solve_s": 199,
      "run_success_rate": 1.0,
      "runs": 1,
      "status": "proved",
      "successes": 1,
      "successes_per_recorded_hour": 18.09,
      "total_solve_s": 199
    },
    {
      "attempt_yield": 1.0,
      "attempts": 1,
      "difficulty": 2,
      "failed_attempts": 0,
      "failures": 0,
      "goal": "sum-range-choose-mul-two-pow",
      "median_solve_s": 188,
      "p90_solve_s": 188,
      "run_success_rate": 1.0,
      "runs": 1,
      "status": "proved",
      "successes": 1,
      "successes_per_recorded_hour": 19.149,
      "total_solve_s": 188
    },
    {
      "attempt_yield": 1.0,
      "attempts": 1,
      "difficulty": 1,
      "failed_attempts": 0,
      "failures": 0,
      "goal": "discriminant-nonneg-s1",
      "median_solve_s": 183,
      "p90_solve_s": 183,
      "run_success_rate": 1.0,
      "runs": 1,
      "status": "proved",
      "successes": 1,
      "successes_per_recorded_hour": 19.672,
      "total_solve_s": 183
    },
    {
      "attempt_yield": 1.0,
      "attempts": 1,
      "difficulty": 3,
      "failed_attempts": 0,
      "failures": 0,
      "goal": "eight-sum-pow-four-ge-sum-pow-four",
      "median_solve_s": 180,
      "p90_solve_s": 180,
      "run_success_rate": 1.0,
      "runs": 1,
      "status": "proved",
      "successes": 1,
      "successes_per_recorded_hour": 20.0,
      "total_solve_s": 180
    },
    {
      "attempt_yield": 1.0,
      "attempts": 1,
      "difficulty": 3,
      "failed_attempts": 0,
      "failures": 0,
      "goal": "dvd-66-pow-eleven-sub-self",
      "median_solve_s": 179,
      "p90_solve_s": 179,
      "run_success_rate": 1.0,
      "runs": 1,
      "status": "proved",
      "successes": 1,
      "successes_per_recorded_hour": 20.112,
      "total_solve_s": 179
    },
    {
      "attempt_yield": 1.0,
      "attempts": 1,
      "difficulty": 2,
      "failed_attempts": 0,
      "failures": 0,
      "goal": "coprime-2n1-3n2",
      "median_solve_s": 171,
      "p90_solve_s": 171,
      "run_success_rate": 1.0,
      "runs": 1,
      "status": "proved",
      "successes": 1,
      "successes_per_recorded_hour": 21.053,
      "total_solve_s": 171
    },
    {
      "attempt_yield": 1.0,
      "attempts": 1,
      "difficulty": 1,
      "failed_attempts": 0,
      "failures": 0,
      "goal": "discriminant-nonneg-s3",
      "median_solve_s": 170,
      "p90_solve_s": 170,
      "run_success_rate": 1.0,
      "runs": 1,
      "status": "proved",
      "successes": 1,
      "successes_per_recorded_hour": 21.176,
      "total_solve_s": 170
    },
    {
      "attempt_yield": 1.0,
      "attempts": 1,
      "difficulty": 3,
      "failed_attempts": 0,
      "failures": 0,
      "goal": "dvd-nine-pow-nine-sub-pow-three",
      "median_solve_s": 170,
      "p90_solve_s": 170,
      "run_success_rate": 1.0,
      "runs": 1,
      "status": "proved",
      "successes": 1,
      "successes_per_recorded_hour": 21.176,
      "total_solve_s": 170
    },
    {
      "attempt_yield": 1.0,
      "attempts": 1,
      "difficulty": 3,
      "failed_attempts": 0,
      "failures": 0,
      "goal": "dvd-30-pow-nine-sub-self",
      "median_solve_s": 163,
      "p90_solve_s": 163,
      "run_success_rate": 1.0,
      "runs": 1,
      "status": "proved",
      "successes": 1,
      "successes_per_recorded_hour": 22.086,
      "total_solve_s": 163
    },
    {
      "attempt_yield": 1.0,
      "attempts": 1,
      "difficulty": 2,
      "failed_attempts": 0,
      "failures": 0,
      "goal": "aurifeuillian-quartic-dvd",
      "median_solve_s": 150,
      "p90_solve_s": 150,
      "run_success_rate": 1.0,
      "runs": 1,
      "status": "proved",
      "successes": 1,
      "successes_per_recorded_hour": 24.0,
      "total_solve_s": 150
    }
  ],
  "historical_attribution": {
    "alias_file": "docs/metrics/contributor-aliases.json",
    "author_count": 8,
    "authors": [
      {
        "attribution_source": "git-add-author",
        "avatar_url": "https://github.com/cgbarlow.png?size=96",
        "difficulty_points": 168,
        "display_name": "Chris Barlow",
        "git_author": "Chris Barlow <cgbarlow@gmail.com>",
        "git_author_name": "Chris Barlow",
        "github": "cgbarlow",
        "index_files_added": 98,
        "missing_solver_provenance": 46,
        "profile_url": "https://github.com/cgbarlow",
        "sample_add_commit": "09c580b287cedf6ba277b154d6473f51cffcdf10",
        "sample_add_date": "2026-06-15",
        "solver_credit": false,
        "solver_provenance_proofs": 52
      },
      {
        "attribution_source": "git-add-author",
        "avatar_url": "https://github.com/chat-bit-01.png?size=96",
        "difficulty_points": 87,
        "display_name": "chat-bit-01",
        "git_author": "chat-bit-01 <chatuser55@gmail.com>",
        "git_author_name": "chat-bit-01",
        "github": "chat-bit-01",
        "index_files_added": 43,
        "missing_solver_provenance": 43,
        "profile_url": "https://github.com/chat-bit-01",
        "sample_add_commit": "93e1b76c5a3b47919904343b52f181913dc8c67d",
        "sample_add_date": "2026-06-15",
        "solver_credit": false,
        "solver_provenance_proofs": 0
      },
      {
        "attribution_source": "git-add-author",
        "avatar_url": null,
        "difficulty_points": 35,
        "display_name": "Perttu Isotalo",
        "git_author": "Perttu Isotalo <pisotalo@isotalo.org>",
        "git_author_name": "Perttu Isotalo",
        "github": null,
        "index_files_added": 18,
        "missing_solver_provenance": 3,
        "profile_url": null,
        "sample_add_commit": "0f1c894d065aadb5069285c190fed864e479fe91",
        "sample_add_date": "2026-06-14",
        "solver_credit": false,
        "solver_provenance_proofs": 15
      },
      {
        "attribution_source": "git-add-author",
        "avatar_url": "https://github.com/binto.png?size=96",
        "difficulty_points": 19,
        "display_name": "binto",
        "git_author": "binto <marcjvincent@gmail.com>",
        "git_author_name": "binto",
        "github": "binto",
        "index_files_added": 9,
        "missing_solver_provenance": 9,
        "profile_url": "https://github.com/binto",
        "sample_add_commit": "386cd2b8a1ca5187b159090f4dfbd7b2f6d4b21e",
        "sample_add_date": "2026-06-12",
        "solver_credit": false,
        "solver_provenance_proofs": 0
      },
      {
        "attribution_source": "git-add-author",
        "avatar_url": null,
        "difficulty_points": 6,
        "display_name": "Adam Holt",
        "git_author": "Adam Holt <adam@adamholt.co.nz>",
        "git_author_name": "Adam Holt",
        "github": null,
        "index_files_added": 4,
        "missing_solver_provenance": 0,
        "profile_url": null,
        "sample_add_commit": "f404fd672dcede78ba2bff365ad3e04a198ca1e0",
        "sample_add_date": "2026-06-14",
        "solver_credit": false,
        "solver_provenance_proofs": 4
      },
      {
        "attribution_source": "git-add-author",
        "avatar_url": null,
        "difficulty_points": 4,
        "display_name": "adam91holt",
        "git_author": "adam91holt <mail@adamholt.co.nz>",
        "git_author_name": "adam91holt",
        "github": null,
        "index_files_added": 2,
        "missing_solver_provenance": 0,
        "profile_url": null,
        "sample_add_commit": "9d8abcf3a675d9669c9979b791a9aee300071e7d",
        "sample_add_date": "2026-06-15",
        "solver_credit": false,
        "solver_provenance_proofs": 2
      },
      {
        "attribution_source": "git-add-author",
        "avatar_url": "https://github.com/OceanLi.png?size=96",
        "difficulty_points": 3,
        "display_name": "OceanLi",
        "git_author": "OceanLi <quantocean.li@gmail.com>",
        "git_author_name": "OceanLi",
        "github": "OceanLi",
        "index_files_added": 1,
        "missing_solver_provenance": 1,
        "profile_url": "https://github.com/OceanLi",
        "sample_add_commit": "83b412048758cb0ebc2337e5750030df1c9ae775",
        "sample_add_date": "2026-06-11",
        "solver_credit": false,
        "solver_provenance_proofs": 0
      },
      {
        "attribution_source": "git-add-author",
        "avatar_url": null,
        "difficulty_points": 1,
        "display_name": "yarcles",
        "git_author": "yarcles <steve.kurzeja@gmail.com>",
        "git_author_name": "yarcles",
        "github": null,
        "index_files_added": 1,
        "missing_solver_provenance": 0,
        "profile_url": null,
        "sample_add_commit": "3d1ea4a2ffdc4d507aeaccebe1118e4685d5afb3",
        "sample_add_date": "2026-06-14",
        "solver_credit": false,
        "solver_provenance_proofs": 1
      }
    ],
    "git_attributed_index_files": 176,
    "records": 176,
    "scope": "library/index/*.aisp",
    "source": "git-add-author",
    "unattributed_index_files": 0
  },
  "models": [
    {
      "attempt_yield": 0.7188,
      "attempts": 64,
      "failed_attempts": 18,
      "failures": 3,
      "median_solve_s": 287,
      "p90_solve_s": 1103,
      "provider_model": "claude / opus",
      "run_success_rate": 0.9388,
      "runs": 49,
      "solvers": 3,
      "successes": 46,
      "successes_per_recorded_hour": 7.452,
      "total_solve_s": 22222,
      "verified_proofs": 43
    },
    {
      "attempt_yield": 0.1224,
      "attempts": 98,
      "failed_attempts": 86,
      "failures": 82,
      "median_solve_s": 282,
      "p90_solve_s": 1904,
      "provider_model": "openai / leanstral-2603",
      "run_success_rate": 0.1277,
      "runs": 94,
      "solvers": 1,
      "successes": 12,
      "successes_per_recorded_hour": 0.702,
      "total_solve_s": 61569,
      "verified_proofs": 10
    },
    {
      "attempt_yield": 0.1579,
      "attempts": 57,
      "failed_attempts": 48,
      "failures": 25,
      "median_solve_s": 332,
      "p90_solve_s": 837,
      "provider_model": "codex / unknown",
      "run_success_rate": 0.2647,
      "runs": 34,
      "solvers": 2,
      "successes": 9,
      "successes_per_recorded_hour": 1.811,
      "total_solve_s": 17892,
      "verified_proofs": 9
    },
    {
      "attempt_yield": 0.6,
      "attempts": 15,
      "failed_attempts": 6,
      "failures": 2,
      "median_solve_s": 375,
      "p90_solve_s": 575,
      "provider_model": "gemini / gemini-3.1-pro-preview",
      "run_success_rate": 0.8182,
      "runs": 11,
      "solvers": 1,
      "successes": 9,
      "successes_per_recorded_hour": 7.192,
      "total_solve_s": 4505,
      "verified_proofs": 7
    },
    {
      "attempt_yield": null,
      "attempts": 0,
      "failed_attempts": 0,
      "failures": 0,
      "median_solve_s": null,
      "p90_solve_s": null,
      "provider_model": "manual / gpt-5.5",
      "run_success_rate": null,
      "runs": 0,
      "solvers": 1,
      "successes": 0,
      "successes_per_recorded_hour": null,
      "total_solve_s": 0,
      "verified_proofs": 4
    },
    {
      "attempt_yield": null,
      "attempts": 0,
      "failed_attempts": 0,
      "failures": 0,
      "median_solve_s": null,
      "p90_solve_s": null,
      "provider_model": "claude / unknown",
      "run_success_rate": null,
      "runs": 0,
      "solvers": 1,
      "successes": 0,
      "successes_per_recorded_hour": null,
      "total_solve_s": 0,
      "verified_proofs": 1
    },
    {
      "attempt_yield": 0.0,
      "attempts": 13,
      "failed_attempts": 13,
      "failures": 13,
      "median_solve_s": 1914,
      "p90_solve_s": 1932,
      "provider_model": "openai / jackcloudman/Leanstral-2603-GGUF",
      "run_success_rate": 0.0,
      "runs": 13,
      "solvers": 1,
      "successes": 0,
      "successes_per_recorded_hour": 0.0,
      "total_solve_s": 24863,
      "verified_proofs": 0
    },
    {
      "attempt_yield": 0.0,
      "attempts": 3,
      "failed_attempts": 3,
      "failures": 1,
      "median_solve_s": 94,
      "p90_solve_s": 94,
      "provider_model": "codex / gpt-5.3-codex-spark",
      "run_success_rate": 0.0,
      "runs": 1,
      "solvers": 1,
      "successes": 0,
      "successes_per_recorded_hour": 0.0,
      "total_solve_s": 94,
      "verified_proofs": 0
    },
    {
      "attempt_yield": 0.0,
      "attempts": 1,
      "failed_attempts": 1,
      "failures": 1,
      "median_solve_s": 82,
      "p90_solve_s": 82,
      "provider_model": "openai / leanstral-2603-sovereign",
      "run_success_rate": 0.0,
      "runs": 1,
      "solvers": 1,
      "successes": 0,
      "successes_per_recorded_hour": 0.0,
      "total_solve_s": 82,
      "verified_proofs": 0
    }
  ],
  "outcome_counts": {
    "decomposed": 16,
    "failed": 111,
    "proved": 76
  },
  "outcomes": {
    "attempt_yield": 0.3028,
    "attempts": 251,
    "failed_attempts": 175,
    "failures": 127,
    "median_solve_s": 303,
    "p90_solve_s": 1903,
    "run_success_rate": 0.3744,
    "runs": 203,
    "successes": 76,
    "successes_per_recorded_hour": 2.085,
    "total_solve_s": 131227
  },
  "queue": {
    "difficulty_counts": {
      "0": 10,
      "1": 87,
      "2": 152,
      "3": 131,
      "4": 25,
      "5": 1
    },
    "goals": 406,
    "status_counts": {
      "archived": 80,
      "blocked": 7,
      "open": 215,
      "proved": 94,
      "translated": 10
    }
  },
  "recent_runs": [
    {
      "agent": "thebeast-ace7",
      "attempts": 1,
      "difficulty": 2,
      "effort": "xhigh",
      "ended": "2026-06-15T05:42:36Z",
      "goal": "bezout-eleven-thirteen-eq-one",
      "id": "20260615t054236773677z-fc5bccf0",
      "model": null,
      "outcome": "failed",
      "provider": "codex",
      "solve_s": 290,
      "solver": "adam91holt"
    },
    {
      "agent": "thebeast-ace7",
      "attempts": 1,
      "difficulty": 2,
      "effort": "xhigh",
      "ended": "2026-06-15T05:36:23Z",
      "goal": "fib-add-three-eq-two-mul-fib-succ-add-fib",
      "id": "20260615t053623449113z-7522451c",
      "model": null,
      "outcome": "failed",
      "provider": "codex",
      "solve_s": 394,
      "solver": "adam91holt"
    },
    {
      "agent": "thebeast-ace7",
      "attempts": 1,
      "difficulty": 2,
      "effort": "xhigh",
      "ended": "2026-06-15T05:17:41Z",
      "goal": "fib-add-six-eq-eight-mul-fib-succ-add-five-mul-fib",
      "id": "20260615t051741928782z-aed18af5",
      "model": null,
      "outcome": "failed",
      "provider": "codex",
      "solve_s": 400,
      "solver": "adam91holt"
    },
    {
      "agent": "sovereign-engine",
      "attempts": 1,
      "difficulty": 2,
      "effort": "high",
      "ended": "2026-06-15T05:17:04Z",
      "goal": "dvd-twentyfour-pow-six-sub-pow-four",
      "id": "20260615t051704142124z-4b7f70f1",
      "model": "jackcloudman/Leanstral-2603-GGUF",
      "outcome": "failed",
      "provider": "openai",
      "solve_s": 1922,
      "solver": "cgbarlow"
    },
    {
      "agent": "afnz-zbook-b336",
      "attempts": 1,
      "difficulty": 2,
      "effort": "high",
      "ended": "2026-06-15T05:09:30Z",
      "goal": "coprime-n-sq-n-add-one",
      "id": "20260615t050930286732z-8ae635c8",
      "model": "leanstral-2603",
      "outcome": "proved",
      "provider": "openai",
      "solve_s": 383,
      "solver": "cgbarlow"
    },
    {
      "agent": "thebeast-ace7",
      "attempts": 1,
      "difficulty": 2,
      "effort": "xhigh",
      "ended": "2026-06-15T05:09:17Z",
      "goal": "fib-add-four-eq-three-mul-fib-add-two-sub-fib",
      "id": "20260615t050917813685z-bf6fc185",
      "model": null,
      "outcome": "failed",
      "provider": "codex",
      "solve_s": 448,
      "solver": "adam91holt"
    },
    {
      "agent": "afnz-zbook-b336",
      "attempts": 1,
      "difficulty": 2,
      "effort": "high",
      "ended": "2026-06-15T05:02:55Z",
      "goal": "fib-add-four-eq-three-mul-fib-add-two-sub-fib",
      "id": "20260615t050255713824z-64d726d5",
      "model": "leanstral-2603",
      "outcome": "failed",
      "provider": "openai",
      "solve_s": 232,
      "solver": "cgbarlow"
    },
    {
      "agent": "afnz-zbook-b336",
      "attempts": 1,
      "difficulty": 2,
      "effort": "high",
      "ended": "2026-06-15T04:57:05Z",
      "goal": "fib-add-five-eq-five-mul-fib-succ-add-three-mul-fib",
      "id": "20260615t045705718756z-2f8a512f",
      "model": "leanstral-2603",
      "outcome": "failed",
      "provider": "openai",
      "solve_s": 414,
      "solver": "cgbarlow"
    },
    {
      "agent": "thebeast-ace7",
      "attempts": 1,
      "difficulty": 2,
      "effort": "xhigh",
      "ended": "2026-06-15T04:49:21Z",
      "goal": "dvd-sixty-pow-ten-sub-sq",
      "id": "20260615t044921384460z-eefcd977",
      "model": null,
      "outcome": "failed",
      "provider": "codex",
      "solve_s": 403,
      "solver": "adam91holt"
    },
    {
      "agent": "afnz-zbook-b336",
      "attempts": 1,
      "difficulty": 2,
      "effort": "high",
      "ended": "2026-06-15T04:48:25Z",
      "goal": "dvd-twentyfour-pow-five-sub-pow-three",
      "id": "20260615t044825370727z-67fe8aee",
      "model": "leanstral-2603",
      "outcome": "failed",
      "provider": "openai",
      "solve_s": 1887,
      "solver": "cgbarlow"
    },
    {
      "agent": "sovereign-engine",
      "attempts": 1,
      "difficulty": 2,
      "effort": "high",
      "ended": "2026-06-15T04:43:09Z",
      "goal": "dvd-sixty-pow-ten-sub-sq",
      "id": "20260615t044309253760z-5a0c355e",
      "model": "jackcloudman/Leanstral-2603-GGUF",
      "outcome": "failed",
      "provider": "openai",
      "solve_s": 1935,
      "solver": "cgbarlow"
    },
    {
      "agent": "thebeast-ace7",
      "attempts": 1,
      "difficulty": 2,
      "effort": "xhigh",
      "ended": "2026-06-15T04:41:05Z",
      "goal": "dvd-twentyfour-pow-seven-sub-pow-five",
      "id": "20260615t044105755342z-0ec5d2c1",
      "model": null,
      "outcome": "failed",
      "provider": "codex",
      "solve_s": 530,
      "solver": "adam91holt"
    },
    {
      "agent": "afnz-zbook-b336",
      "attempts": 1,
      "difficulty": 3,
      "effort": "high",
      "ended": "2026-06-15T04:15:07Z",
      "goal": "cyclic-quad-ge-abc-times-sum",
      "id": "20260615t041507542997z-762a26bd",
      "model": "leanstral-2603",
      "outcome": "failed",
      "provider": "openai",
      "solve_s": 1883,
      "solver": "cgbarlow"
    },
    {
      "agent": "sovereign-engine",
      "attempts": 1,
      "difficulty": 4,
      "effort": "high",
      "ended": "2026-06-15T04:07:01Z",
      "goal": "no-nat-sq-eq-two-mul-sq",
      "id": "20260615t040700904406z-1422e085",
      "model": "jackcloudman/Leanstral-2603-GGUF",
      "outcome": "failed",
      "provider": "openai",
      "solve_s": 1902,
      "solver": "cgbarlow"
    },
    {
      "agent": "thebeast-ace7",
      "attempts": 1,
      "difficulty": 2,
      "effort": "xhigh",
      "ended": "2026-06-15T03:52:31Z",
      "goal": "dvd-sixty-pow-six-sub-sq",
      "id": "20260615t035231904431z-3586fa54",
      "model": null,
      "outcome": "failed",
      "provider": "codex",
      "solve_s": 429,
      "solver": "adam91holt"
    },
    {
      "agent": "thebeast-ace7",
      "attempts": 1,
      "difficulty": 1,
      "effort": "xhigh",
      "ended": "2026-06-15T03:43:16Z",
      "goal": "four-var-qm-am-s2",
      "id": "20260615t034316755101z-cdfbd83f",
      "model": null,
      "outcome": "failed",
      "provider": "codex",
      "solve_s": 238,
      "solver": "adam91holt"
    },
    {
      "agent": "afnz-zbook-b336",
      "attempts": 1,
      "difficulty": 1,
      "effort": "high",
      "ended": "2026-06-15T03:41:46Z",
      "goal": "four-var-qm-am-s3",
      "id": "20260615t034146396872z-6ad785b1",
      "model": "leanstral-2603",
      "outcome": "proved",
      "provider": "openai",
      "solve_s": 542,
      "solver": "cgbarlow"
    },
    {
      "agent": "sovereign-engine",
      "attempts": 1,
      "difficulty": 2,
      "effort": "high",
      "ended": "2026-06-15T03:34:47Z",
      "goal": "coprime-2n1-2n3",
      "id": "20260615t033447026105z-98c6a6af",
      "model": "jackcloudman/Leanstral-2603-GGUF",
      "outcome": "failed",
      "provider": "openai",
      "solve_s": 1914,
      "solver": "cgbarlow"
    },
    {
      "agent": "afnz-zbook-b336",
      "attempts": 1,
      "difficulty": 2,
      "effort": "high",
      "ended": "2026-06-15T03:32:30Z",
      "goal": "coprime-3n1-4n1",
      "id": "20260615t033229961874z-cac7cfa8",
      "model": "leanstral-2603",
      "outcome": "failed",
      "provider": "openai",
      "solve_s": 1961,
      "solver": "cgbarlow"
    },
    {
      "agent": "thebeast-ace7",
      "attempts": 1,
      "difficulty": 1,
      "effort": "xhigh",
      "ended": "2026-06-15T03:26:42Z",
      "goal": "four-var-qm-am-s2",
      "id": "20260615t032642628829z-d76d18dd",
      "model": null,
      "outcome": "failed",
      "provider": "codex",
      "solve_s": 277,
      "solver": "adam91holt"
    }
  ],
  "schema_version": 1
}
